{
  "base_process_rate": 2.0,
  "description": "CAPE spike simulation scenarios for testing weight adaptation",
  
  "scenarios": [
    {
      "name": "ml_morning_training",
      "description": "Daily ML training jobs - weekdays 8:30-9:30 AM with jitter",
      "pattern": {
        "type": "daily_with_schedule",
        "base_time": "08:45:00",
        "time_jitter_minutes": 15,
        "duration_minutes": 45,
        "duration_jitter_minutes": 10,
        "process_rate_multiplier": 8.0,
        "active_days": ["monday", "tuesday", "wednesday", "thursday", "friday"],
        "active_hours": [8, 9, 10],
        "probability": 0.85,
        "executor_type": "ml",
        "priority_distribution": [7, 8, 8, 9, 9],
        "data_location": "iceland",
        "data_size_gb": 500.0
      }
    },
    {
      "name": "iot_sensor_bursts",
      "description": "IoT sensor data bursts - random but more frequent during business hours",
      "pattern": {
        "type": "poisson_with_schedule",
        "base_interval_minutes": 90,
        "interval_jitter_minutes": 30,
        "duration_minutes": 12,
        "duration_jitter_minutes": 8,
        "process_rate_multiplier": 15.0,
        "active_hours": [6, 7, 8, 9, 10, 11, 12, 13, 14, 15, 16, 17, 18, 19, 20],
        "weekend_rate_reduction": 0.3,
        "probability": 0.7,
        "executor_type": "edge",
        "priority_distribution": [8, 9, 9, 10],
        "data_location": "stockholm",
        "data_size_gb": 5.0
      }
    },
    {
      "name": "evening_batch_processing",
      "description": "End-of-day batch jobs - weekdays 17:30-19:00 with variance",
      "pattern": {
        "type": "daily_with_schedule",
        "base_time": "18:15:00",
        "time_jitter_minutes": 25,
        "duration_minutes": 75,
        "duration_jitter_minutes": 20,
        "process_rate_multiplier": 6.0,
        "active_days": ["monday", "tuesday", "wednesday", "thursday", "friday"],
        "active_hours": [17, 18, 19],
        "probability": 0.95,
        "executor_type": "cloud",
        "priority_distribution": [4, 5, 6, 6, 7],
        "data_location": "aws_east",
        "data_size_gb": 100.0
      }
    },
    {
      "name": "massive_data_processing",
      "description": "Large-scale data processing - irregular massive spikes generating ~100 processes",
      "pattern": {
        "type": "poisson_with_schedule",
        "base_interval_minutes": 180,
        "interval_jitter_minutes": 90,
        "duration_minutes": 30,
        "duration_jitter_minutes": 15,
        "process_rate_multiplier": 25.0,
        "active_hours": [9, 10, 11, 14, 15, 16, 17],
        "active_days": ["monday", "tuesday", "wednesday", "thursday", "friday"],
        "weekend_rate_reduction": 0.2,
        "probability": 0.6,
        "executor_type": "cloud",
        "priority_distribution": [6, 7, 8, 8, 9],
        "data_location": "aws_east",
        "data_size_gb": 800.0
      }
    },
    {
      "name": "weekend_maintenance",
      "description": "Weekend maintenance spikes - Sunday mornings with high variance",
      "pattern": {
        "type": "weekly_with_schedule",
        "base_time": "03:00:00",
        "time_jitter_minutes": 60,
        "duration_minutes": 180,
        "duration_jitter_minutes": 45,
        "process_rate_multiplier": 4.0,
        "active_days": ["sunday"],
        "active_hours": [2, 3, 4, 5, 6],
        "probability": 0.8,
        "executor_type": "cloud",
        "priority_distribution": [3, 4, 5, 6],
        "data_location": "aws_east",
        "data_size_gb": 200.0
      }
    },
    {
      "name": "peak_hour_traffic",
      "description": "Peak hour traffic spikes - lunch and evening with user behavior patterns",
      "pattern": {
        "type": "multi_peak_daily",
        "peaks": [
          {
            "base_time": "12:30:00",
            "time_jitter_minutes": 20,
            "duration_minutes": 30,
            "intensity": 7.0
          },
          {
            "base_time": "19:45:00",
            "time_jitter_minutes": 25,
            "duration_minutes": 40,
            "intensity": 9.0
          }
        ],
        "active_days": ["monday", "tuesday", "wednesday", "thursday", "friday", "saturday"],
        "weekend_intensity_reduction": 0.6,
        "probability": 0.75,
        "executor_type": "edge",
        "priority_distribution": [6, 7, 8, 8, 9],
        "data_location": "stockholm",
        "data_size_gb": 15.0
      }
    },
    {
      "name": "ml_inference_cascades",
      "description": "ML inference triggering downstream processing - irregular patterns",
      "pattern": {
        "type": "cascade_with_schedule",
        "base_interval_minutes": 180,
        "interval_jitter_minutes": 90,
        "cascade_stages": 3,
        "stage_delay_minutes": 5,
        "stage_jitter_minutes": 3,
        "duration_minutes": 25,
        "process_rate_multiplier": 8.0,
        "active_hours": [9, 10, 11, 14, 15, 16],
        "active_days": ["monday", "tuesday", "wednesday", "thursday", "friday"],
        "probability": 0.6,
        "executor_type": "ml",
        "priority_distribution": [7, 8, 9],
        "data_location": "iceland",
        "data_size_gb": 50.0
      }
    },
    {
      "name": "high_priority_emergency",
      "description": "Emergency high-priority processing - rare but massive spikes generating 80-120 processes",
      "pattern": {
        "type": "poisson_with_schedule",
        "base_interval_minutes": 240,
        "interval_jitter_minutes": 120,
        "duration_minutes": 20,
        "duration_jitter_minutes": 10,
        "process_rate_multiplier": 35.0,
        "active_hours": [0, 1, 2, 3, 4, 5, 6, 7, 8, 9, 10, 11, 12, 13, 14, 15, 16, 17, 18, 19, 20, 21, 22, 23],
        "active_days": ["monday", "tuesday", "wednesday", "thursday", "friday", "saturday", "sunday"],
        "weekend_rate_reduction": 0.8,
        "probability": 0.4,
        "executor_type": "edge",
        "priority_distribution": [9, 9, 10, 10],
        "data_location": "stockholm",
        "data_size_gb": 25.0
      }
    }
  ],
  
  "simulation_parameters": {
    "duration_hours": 168,
    "warmup_hours": 24,
    "measurement_interval_minutes": 15,
    "enable_learning": true,
    "initial_exploration_rate": 0.3,
    "target_sla_percentile": 95,
    "max_cost_per_hour": 100.0
  }
}